<?xml version="1.0" encoding="UTF-8"?>
<beans xmlns="http://www.springframework.org/schema/beans"
	xmlns:xsi="http://www.w3.org/2001/XMLSchema-instance"
	xsi:schemaLocation="http://www.springframework.org/schema/beans http://www.springframework.org/schema/beans/spring-beans.xsd">

	<!-- Root Context: defines shared resources visible to all other web components -->
	<!--Data Source Conf -->
	<bean id="mgsdbSource"
		class="org.springframework.jdbc.datasource.DriverManagerDataSource">
		<property name="driverClassName" value="com.mysql.jdbc.Driver" />
		<property name="url" value="jdbc:mysql://54.169.83.168:3306/mgsdb?useUnicode=true&amp;characterEncoding=utf8" />
		<property name="username" value="mgshost" />
		<property name="password" value="@Nintendo64" />
	</bean>
	
	<bean id="staffManager" class="com.n8ify.mgs.stffp.dealer.StaffManager">
		<property name="dataSource" ref="mgsdbSource" />
	</bean>
</beans>
